pySWATPlus/__init__.py
pySWATPlus/calibration.py
pySWATPlus/cpu.py
pySWATPlus/data_manager.py
pySWATPlus/newtype.py
pySWATPlus/performance_metrics.py
pySWATPlus/sensitivity_analyzer.py
pySWATPlus/txtinout_reader.py
pySWATPlus/utils.py
pySWATPlus/validators.py
pyswatplus-1.3.0.dist-info/licenses/LICENSE
pyswatplus-1.3.0.dist-info/METADATA
pyswatplus-1.3.0.dist-info/WHEEL
pyswatplus-1.3.0.dist-info/top_level.txt
pyswatplus-1.3.0.dist-info/RECORD
