Metadata-Version: 2.4
Name: pySWATPlus
Version: 1.3.0
Summary: A Python interface for interacting with the SWAT+ hydrological model
Author-email: Joan Saló <joansalograu@gmail.com>, Debasish Pal <bestdebasish@gmail.com>
License-Expression: GPL-3.0-or-later
Project-URL: Homepage, https://github.com/swat-model/pySWATPlus
Project-URL: Documentation, https://swat-model.github.io/pySWATPlus/
Keywords: SWAT+,simulation,hydrology,watershed
Classifier: Development Status :: 4 - Beta
Classifier: Programming Language :: Python :: 3
Classifier: Programming Language :: Python :: 3.13
Classifier: Programming Language :: Python :: 3.12
Classifier: Programming Language :: Python :: 3.11
Classifier: Programming Language :: Python :: 3.10
Classifier: Operating System :: OS Independent
Classifier: Intended Audience :: Science/Research
Classifier: Topic :: Scientific/Engineering
Classifier: Topic :: Scientific/Engineering :: Hydrology
Requires-Python: <3.14,>=3.10
License-File: LICENSE
Requires-Dist: pydantic
Requires-Dist: SALib
Requires-Dist: pymoo
Dynamic: license-file
